Metadata-Version: 2.1
Name: neospy
Version: 0.0.2
Summary: A Python module to interface with the NEOS optimization servers.
Home-page: https://github.com/scythetrigger/neospy
Author: Nicholas Parham
Author-email: nick-99@att.net
License: Apache Software License
Platform: UNKNOWN
